{
  "beneficialOwners": [
    {
      "name": "Yaochu Yang",
      "beneficiaryType": { "description": "Individual" },
      "address": { "city": "Unknown", "country": "Unknown" },
      "beneficialOwnershipPercentage": 0.35,
      "degreeOfSeparation": 1
    },
    {
      "name": "Shaoteng Duan",
      "beneficiaryType": { "description": "Individual" },
      "address": { "city": "Unknown", "country": "Unknown" },
      "beneficialOwnershipPercentage": 0.3,
      "degreeOfSeparation": 1
    },
    {
      "name": "Zhong Wang",
      "beneficiaryType": { "description": "Individual" },
      "address": { "city": "Unknown", "country": "Unknown" },
      "beneficialOwnershipPercentage": 0.24,
      "degreeOfSeparation": 1
    },
    {
      "name": "Simo He",
      "beneficiaryType": { "description": "Individual" },
      "address": { "city": "Unknown", "country": "Unknown" },
      "beneficialOwnershipPercentage": 0.17,
      "degreeOfSeparation": 1
    },
    {
      "name": "Furong Mai",
      "beneficiaryType": { "description": "Individual" },
      "address": { "city": "Unknown", "country": "Unknown" },
      "beneficialOwnershipPercentage": 0.23,
      "degreeOfSeparation": 1
    }
  ]
}
